[
  {
    "school_osm_id": "-7825262",
    "school_osm_type": "relation",
    "school_name": "Школа № 30",
    "place_osm_id": "-167857",
    "place_admin_level": "6",
    "place_place": "city",
    "place_name": "Бобруйск",
    "lon": "29.193724930288404",
    "lat": "53.16330823922403",
    "bbox": "29.192351999999993,53.16241139909452,29.1950984,53.164186299094624"
  },
  {
    "school_osm_id": "-7825261",
    "school_osm_type": "relation",
    "school_name": "Гимназия № 1",
    "place_osm_id": "-167857",
    "place_admin_level": "6",
    "place_place": "city",
    "place_name": "Бобруйск",
    "lon": "29.192881414067067",
    "lat": "53.16236835088405",
    "bbox": "29.191029699999998,53.16111929909447,29.195294799999996,53.16365729909459"
  },
  {
    "school_osm_id": "-3658867",
    "school_osm_type": "relation",
    "school_name": "СШ №2",
    "place_osm_id": "-167857",
    "place_admin_level": "6",
    "place_place": "city",
    "place_name": "Бобруйск",
    "lon": "29.231182108305944",
    "lat": "53.14514016836615",
    "bbox": "29.231883899999996,53.145544499093674,29.230454799999993,53.144763799093646"
  },
  {
    "school_osm_id": "203701416",
    "school_osm_type": "way",
    "school_name": "Средняя школа №12",
    "place_osm_id": "-167857",
    "place_admin_level": "6",
    "place_place": "city",
    "place_name": "Бобруйск",
    "lon": "29.22425911679729",
    "lat": "53.118303057328106",
    "bbox": "29.2239099,53.11810639909238,29.2245937,53.11851279909238"
  },
  {
    "school_osm_id": "205058743",
    "school_osm_type": "way",
    "school_name": "Школа № 26",
    "place_osm_id": "-167857",
    "place_admin_level": "6",
    "place_place": "city",
    "place_name": "Бобруйск",
    "lon": "29.21665848516356",
    "lat": "53.152864103703685",
    "bbox": "29.2160067,53.152378799093995,29.217486700000002,53.15338589909407"
  },
  {
    "school_osm_id": "205059341",
    "school_osm_type": "way",
    "school_name": "Ясли-Сад № 51",
    "place_osm_id": "-167857",
    "place_admin_level": "6",
    "place_place": "city",
    "place_name": "Бобруйск",
    "lon": "29.215675040724598",
    "lat": "53.155313334893506",
    "bbox": "29.215244,53.155035499094154,29.2161583,53.155569399094176"
  },
  {
    "school_osm_id": "223011977",
    "school_osm_type": "way",
    "school_name": "",
    "place_osm_id": "-167857",
    "place_admin_level": "6",
    "place_place": "city",
    "place_name": "Бобруйск",
    "lon": "29.200447249354553",
    "lat": "53.16634551451031",
    "bbox": "29.2021233,53.16727329909477,29.1987712,53.16541769909468"
  },
  {
    "school_osm_id": "223129752",
    "school_osm_type": "way",
    "school_name": "",
    "place_osm_id": "-167857",
    "place_admin_level": "6",
    "place_place": "city",
    "place_name": "Бобруйск",
    "lon": "29.194454852337753",
    "lat": "53.1730984782012",
    "bbox": "29.192566499999998,53.17198469909502,29.196521700000005,53.174193499095146"
  },
  {
    "school_osm_id": "223132009",
    "school_osm_type": "way",
    "school_name": "",
    "place_osm_id": "-167857",
    "place_admin_level": "6",
    "place_place": "city",
    "place_name": "Бобруйск",
    "lon": "29.227030562982115",
    "lat": "53.195669140169834",
    "bbox": "29.2284784,53.19715999909641,29.22551869999999,53.194181399096216"
  },
  {
    "school_osm_id": "274897533",
    "school_osm_type": "way",
    "school_name": "Школа № 6",
    "place_osm_id": "-167857",
    "place_admin_level": "6",
    "place_place": "city",
    "place_name": "Бобруйск",
    "lon": "29.213745295058843",
    "lat": "53.14685002470695",
    "bbox": "29.215503899999998,53.1478591990938,29.211824399999998,53.14605359909369"
  },
  {
    "school_osm_id": "274903337",
    "school_osm_type": "way",
    "school_name": "Школа № 1",
    "place_osm_id": "-167857",
    "place_admin_level": "6",
    "place_place": "city",
    "place_name": "Бобруйск",
    "lon": "29.240794344684648",
    "lat": "53.1500619889253",
    "bbox": "29.2388909,53.14922509909386,29.242675099999996,53.15099519909394"
  },
  {
    "school_osm_id": "275257872",
    "school_osm_type": "way",
    "school_name": "СШ № 32",
    "place_osm_id": "-167857",
    "place_admin_level": "6",
    "place_place": "city",
    "place_name": "Бобруйск",
    "lon": "29.229593996262174",
    "lat": "53.196007059641204",
    "bbox": "29.228136899999996,53.195209199096276,29.2310884,53.19682149909639"
  },
  {
    "school_osm_id": "306374305",
    "school_osm_type": "way",
    "school_name": "Гимназия №2",
    "place_osm_id": "-167857",
    "place_admin_level": "6",
    "place_place": "city",
    "place_name": "Бобруйск",
    "lon": "29.232623012104217",
    "lat": "53.15844510845228",
    "bbox": "29.233693499999994,53.15914879909436,29.231714399999994,53.15772559909427"
  },
  {
    "school_osm_id": "306382653",
    "school_osm_type": "way",
    "school_name": "СШ № 28",
    "place_osm_id": "-167857",
    "place_admin_level": "6",
    "place_place": "city",
    "place_name": "Бобруйск",
    "lon": "29.1877355285821",
    "lat": "53.17049860487099",
    "bbox": "29.1857499,53.169154099094875,29.1896468,53.171796599095025"
  },
  {
    "school_osm_id": "330710205",
    "school_osm_type": "way",
    "school_name": "СШ №27",
    "place_osm_id": "-167857",
    "place_admin_level": "6",
    "place_place": "city",
    "place_name": "Бобруйск",
    "lon": "29.2253881329646",
    "lat": "53.147493743059094",
    "bbox": "29.2265507,53.148250899093796,29.2241286,53.146832199093744"
  },
  {
    "school_osm_id": "339702087",
    "school_osm_type": "way",
    "school_name": "",
    "place_osm_id": "-167857",
    "place_admin_level": "6",
    "place_place": "city",
    "place_name": "Бобруйск",
    "lon": "29.231230146243558",
    "lat": "53.1452441312558",
    "bbox": "29.2299666,53.14457779909362,29.23264079999999,53.14607079909371"
  },
  {
    "school_osm_id": "365237676",
    "school_osm_type": "way",
    "school_name": "СШ № 24",
    "place_osm_id": "-167857",
    "place_admin_level": "6",
    "place_place": "city",
    "place_name": "Бобруйск",
    "lon": "29.16929603768546",
    "lat": "53.1576440996143",
    "bbox": "29.1679686,53.15669959909424,29.170645199999992,53.158589499094326"
  },
  {
    "school_osm_id": "443448634",
    "school_osm_type": "way",
    "school_name": "Воскресная школа Храма Святой Мученицы Елизаветы",
    "place_osm_id": "-167857",
    "place_admin_level": "6",
    "place_place": "city",
    "place_name": "Бобруйск",
    "lon": "29.22493875889441",
    "lat": "53.15333248255056",
    "bbox": "29.225529800000004,53.15367939909408,29.224357900000005,53.15297929909405"
  },
  {
    "school_osm_id": "541609547",
    "school_osm_type": "way",
    "school_name": "Средняя школа №25",
    "place_osm_id": "-167857",
    "place_admin_level": "6",
    "place_place": "city",
    "place_name": "Бобруйск",
    "lon": "29.200498886328145",
    "lat": "53.153229530515475",
    "bbox": "29.202002700000005,53.154134399094104,29.1990254,53.15234259909402"
  },
  {
    "school_osm_id": "578001621",
    "school_osm_type": "way",
    "school_name": "",
    "place_osm_id": "-167857",
    "place_admin_level": "6",
    "place_place": "city",
    "place_name": "Бобруйск",
    "lon": "29.231332729471934",
    "lat": "53.180249341124025",
    "bbox": "29.230091600000005,53.17963319909544,29.232800600000004,53.18102199909551"
  },
  {
    "school_osm_id": "666370816",
    "school_osm_type": "way",
    "school_name": "Средняя школа № 29",
    "place_osm_id": "-167857",
    "place_admin_level": "6",
    "place_place": "city",
    "place_name": "Бобруйск",
    "lon": "29.180577777916046",
    "lat": "53.13877613210177",
    "bbox": "29.1819039,53.13938369909338,29.17925169999999,53.13816859909332"
  },
  {
    "school_osm_id": "735279625",
    "school_osm_type": "way",
    "school_name": "Гимназия 3",
    "place_osm_id": "-167857",
    "place_admin_level": "6",
    "place_place": "city",
    "place_name": "Бобруйск",
    "lon": "29.22596557677325",
    "lat": "53.14272525781229",
    "bbox": "29.226823900000003,53.14327389909355,29.2251466,53.14212159909352"
  },
  {
    "school_osm_id": "771883218",
    "school_osm_type": "way",
    "school_name": "Школа №18",
    "place_osm_id": "-167857",
    "place_admin_level": "6",
    "place_place": "city",
    "place_name": "Бобруйск",
    "lon": "29.22316823493423",
    "lat": "53.15417743227266",
    "bbox": "29.222168,53.15347649909406,29.224145099999998,53.15496909909414"
  },
  {
    "school_osm_id": "771883220",
    "school_osm_type": "way",
    "school_name": "",
    "place_osm_id": "-167857",
    "place_admin_level": "6",
    "place_place": "city",
    "place_name": "Бобруйск",
    "lon": "29.22196286241174",
    "lat": "53.15514195324644",
    "bbox": "29.220595099999993,53.1541487990941,29.2234746,53.1561029990942"
  },
  {
    "school_osm_id": "816170561",
    "school_osm_type": "way",
    "school_name": "",
    "place_osm_id": "-167857",
    "place_admin_level": "6",
    "place_place": "city",
    "place_name": "Бобруйск",
    "lon": "29.24122709841933",
    "lat": "53.11174763130606",
    "bbox": "29.2393355,53.11088889909204,29.242786100000004,53.11278409909213"
  },
  {
    "school_osm_id": "816553241",
    "school_osm_type": "way",
    "school_name": "",
    "place_osm_id": "-167857",
    "place_admin_level": "6",
    "place_place": "city",
    "place_name": "Бобруйск",
    "lon": "29.192858617881306",
    "lat": "53.13352932914953",
    "bbox": "29.193422300000005,53.134415599093124,29.192284199999992,53.13270829909305"
  },
  {
    "school_osm_id": "2415611390",
    "school_osm_type": "node",
    "school_name": "Школа для детей с нарушением слуха",
    "place_osm_id": "-167857",
    "place_admin_level": "6",
    "place_place": "city",
    "place_name": "Бобруйск",
    "lon": "29.2303097",
    "lat": "53.13537709909318",
    "bbox": ""
  },
  {
    "school_osm_id": "2415620583",
    "school_osm_type": "node",
    "school_name": "Школа 19",
    "place_osm_id": "-167857",
    "place_admin_level": "6",
    "place_place": "city",
    "place_name": "Бобруйск",
    "lon": "29.2020836",
    "lat": "53.13754179909329",
    "bbox": ""
  },
  {
    "school_osm_id": "2416506342",
    "school_osm_type": "node",
    "school_name": "Автошкола \"БОАМЛ\"",
    "place_osm_id": "-167857",
    "place_admin_level": "6",
    "place_place": "city",
    "place_name": "Бобруйск",
    "lon": "29.210893199999997",
    "lat": "53.14003529909341",
    "bbox": ""
  },
  {
    "school_osm_id": "4226321491",
    "school_osm_type": "node",
    "school_name": "Школа #11",
    "place_osm_id": "-167857",
    "place_admin_level": "6",
    "place_place": "city",
    "place_name": "Бобруйск",
    "lon": "29.2422371",
    "lat": "53.1118735990921",
    "bbox": ""
  },
  {
    "school_osm_id": "4276535495",
    "school_osm_type": "node",
    "school_name": "Школа №18",
    "place_osm_id": "-167857",
    "place_admin_level": "6",
    "place_place": "city",
    "place_name": "Бобруйск",
    "lon": "29.222648999999993",
    "lat": "53.15379279909408",
    "bbox": ""
  },
  {
    "school_osm_id": "4350170425",
    "school_osm_type": "node",
    "school_name": "Бобруйский Технологический Коледж",
    "place_osm_id": "-167857",
    "place_admin_level": "6",
    "place_place": "city",
    "place_name": "Бобруйск",
    "lon": "29.2182887",
    "lat": "53.13919659909338",
    "bbox": ""
  },
  {
    "school_osm_id": "4356487593",
    "school_osm_type": "node",
    "school_name": "\"Бобруйский государственный лесотехнический колледж\"",
    "place_osm_id": "-167857",
    "place_admin_level": "6",
    "place_place": "city",
    "place_name": "Бобруйск",
    "lon": "29.224589300000005",
    "lat": "53.136393899093235",
    "bbox": ""
  },
  {
    "school_osm_id": "4428554991",
    "school_osm_type": "node",
    "school_name": "Средняя школа №23",
    "place_osm_id": "-167857",
    "place_admin_level": "6",
    "place_place": "city",
    "place_name": "Бобруйск",
    "lon": "29.192929299999996",
    "lat": "53.13404249909312",
    "bbox": ""
  },
  {
    "school_osm_id": "4428577390",
    "school_osm_type": "node",
    "school_name": "Базовая школа №15",
    "place_osm_id": "-167857",
    "place_admin_level": "6",
    "place_place": "city",
    "place_name": "Бобруйск",
    "lon": "29.294478499999997",
    "lat": "53.14197919909351",
    "bbox": ""
  },
  {
    "school_osm_id": "4428580389",
    "school_osm_type": "node",
    "school_name": "Средняя школа №3",
    "place_osm_id": "-167857",
    "place_admin_level": "6",
    "place_place": "city",
    "place_name": "Бобруйск",
    "lon": "29.226134800000004",
    "lat": "53.129668099092925",
    "bbox": ""
  },
  {
    "school_osm_id": "4428580390",
    "school_osm_type": "node",
    "school_name": "Средняя школа №4",
    "place_osm_id": "-167857",
    "place_admin_level": "6",
    "place_place": "city",
    "place_name": "Бобруйск",
    "lon": "29.2135331",
    "lat": "53.13247079909305",
    "bbox": ""
  },
  {
    "school_osm_id": "4430365895",
    "school_osm_type": "node",
    "school_name": "Базовая школа №7",
    "place_osm_id": "-167857",
    "place_admin_level": "6",
    "place_place": "city",
    "place_name": "Бобруйск",
    "lon": "29.220505799999998",
    "lat": "53.116678299092285",
    "bbox": ""
  },
  {
    "school_osm_id": "4430554889",
    "school_osm_type": "node",
    "school_name": "Средняя школа №17",
    "place_osm_id": "-167857",
    "place_admin_level": "6",
    "place_place": "city",
    "place_name": "Бобруйск",
    "lon": "29.235074500000003",
    "lat": "53.09611479909141",
    "bbox": ""
  },
  {
    "school_osm_id": "4884761921",
    "school_osm_type": "node",
    "school_name": "Школа N1",
    "place_osm_id": "-167857",
    "place_admin_level": "6",
    "place_place": "city",
    "place_name": "Бобруйск",
    "lon": "29.2410004",
    "lat": "53.1500713990939",
    "bbox": ""
  },
  {
    "school_osm_id": "6703347786",
    "school_osm_type": "node",
    "school_name": "ГУО средняя школа 34",
    "place_osm_id": "-167857",
    "place_admin_level": "6",
    "place_place": "city",
    "place_name": "Бобруйск",
    "lon": "29.1702228",
    "lat": "53.16424179909462",
    "bbox": ""
  },
  {
    "school_osm_id": "6854724186",
    "school_osm_type": "node",
    "school_name": "Гимназия-колледж искусств",
    "place_osm_id": "-167857",
    "place_admin_level": "6",
    "place_place": "city",
    "place_name": "Бобруйск",
    "lon": "29.2216603",
    "lat": "53.15447939909412",
    "bbox": ""
  }
]