[
  {
    "school_osm_id": "188513223",
    "school_osm_type": "way",
    "school_name": "Музыкальная школа",
    "place_osm_id": "-6722391",
    "place_admin_level": "8",
    "place_place": "town",
    "place_name": "Берёзовка",
    "lon": "25.501241194581834",
    "lat": "53.717104562319165",
    "bbox": "25.5014984,53.71722249914371,25.500936399999997,53.71698299914369"
  },
  {
    "school_osm_id": "360153071",
    "school_osm_type": "way",
    "school_name": "СШ №2",
    "place_osm_id": "-6722391",
    "place_admin_level": "8",
    "place_place": "town",
    "place_name": "Берёзовка",
    "lon": "25.508790117254456",
    "lat": "53.72127464852835",
    "bbox": "25.510745499999995,53.72214759914434,25.506866299999995,53.720328799144106"
  },
  {
    "school_osm_id": "816749245",
    "school_osm_type": "way",
    "school_name": "Гимназия №1",
    "place_osm_id": "-6722391",
    "place_admin_level": "8",
    "place_place": "town",
    "place_name": "Берёзовка",
    "lon": "25.503916062165807",
    "lat": "53.71550187530303",
    "bbox": "25.502403899999997,53.71474899914342,25.505399099999998,53.7162367991436"
  },
  {
    "school_osm_id": "816749246",
    "school_osm_type": "way",
    "school_name": "СШ №3",
    "place_osm_id": "-6722391",
    "place_admin_level": "8",
    "place_place": "town",
    "place_name": "Берёзовка",
    "lon": "25.503756925395464",
    "lat": "53.711883174579576",
    "bbox": "25.5054527,53.71287899914317,25.5020732,53.71106859914296"
  }
]