[
  {
    "school_osm_id": "-7079698",
    "school_osm_type": "relation",
    "school_name": "Гимназия № 1",
    "place_osm_id": "-6722644",
    "place_admin_level": "8",
    "place_place": "town",
    "place_name": "Горки",
    "lon": "30.995519756263604",
    "lat": "54.278885855992435",
    "bbox": "30.9948318,54.27838599923658,30.996391799999998,54.2794665992368"
  },
  {
    "school_osm_id": "199789505",
    "school_osm_type": "way",
    "school_name": "СШ №3",
    "place_osm_id": "-6722644",
    "place_admin_level": "8",
    "place_place": "town",
    "place_name": "Горки",
    "lon": "30.991458051636542",
    "lat": "54.27458537188783",
    "bbox": "30.9923052,54.275055699235914,30.9906832,54.27423159923572"
  },
  {
    "school_osm_id": "203445547",
    "school_osm_type": "way",
    "school_name": "Вечерняя школа",
    "place_osm_id": "-6722644",
    "place_admin_level": "8",
    "place_place": "town",
    "place_name": "Горки",
    "lon": "30.981206165198493",
    "lat": "54.293274578103464",
    "bbox": "30.9814392,54.29339509923965,30.980978,54.293158599239646"
  },
  {
    "school_osm_id": "373029137",
    "school_osm_type": "way",
    "school_name": "СШ №1",
    "place_osm_id": "-6722644",
    "place_admin_level": "8",
    "place_place": "town",
    "place_name": "Горки",
    "lon": "30.984071723677317",
    "lat": "54.28627290268806",
    "bbox": "30.983092399999993,54.28576149923809,30.985061099999996,54.28678879923832"
  },
  {
    "school_osm_id": "375902109",
    "school_osm_type": "way",
    "school_name": "",
    "place_osm_id": "-6722644",
    "place_admin_level": "8",
    "place_place": "town",
    "place_name": "Горки",
    "lon": "30.977617191100496",
    "lat": "54.29715776900305",
    "bbox": "30.975751999999996,54.29618519924024,30.979496299999994,54.29806349924065"
  },
  {
    "school_osm_id": "480948238",
    "school_osm_type": "way",
    "school_name": "СШ №2",
    "place_osm_id": "-6722644",
    "place_admin_level": "8",
    "place_place": "town",
    "place_name": "Горки",
    "lon": "30.977794338318763",
    "lat": "54.29014813369439",
    "bbox": "30.976684400000003,54.28952039923887,30.9788864,54.29078849923913"
  }
]