{
  "place": {
    "name": "Ганцевичи",
    "osm_id": "-5602434",
    "hierarchy": [
      "Ганцевичский район",
      "Брестская область"
    ]
  },
  "geo": {
    "lat": "52.751856166456704",
    "lon": "26.41633137497884"
  },
  "group": [
    {
      "school_osm_id": "215232318",
      "school_osm_type": "way",
      "school_name": "",
      "place_osm_id": "-5602434",
      "place_admin_level": "8",
      "place_place": "town",
      "place_name": "Ганцевичи",
      "lon": "26.41633137497884",
      "lat": "52.751856166456704",
      "bbox": "26.4153185,52.751513199084144,26.417356599999998,52.75219179908415"
    },
    {
      "school_osm_id": "215232318",
      "school_osm_type": "way",
      "school_name": "",
      "place_osm_id": "-71121",
      "place_admin_level": "6",
      "place_place": "",
      "place_name": "Ганцевичский район",
      "lon": "26.41633137497884",
      "lat": "52.751856166456704",
      "bbox": "26.4153185,52.751513199084144,26.417356599999998,52.75219179908415"
    },
    {
      "school_osm_id": "215232318",
      "school_osm_type": "way",
      "school_name": "",
      "place_osm_id": "-59189",
      "place_admin_level": "4",
      "place_place": "",
      "place_name": "Брестская область",
      "lon": "26.41633137497884",
      "lat": "52.751856166456704",
      "bbox": "26.4153185,52.751513199084144,26.417356599999998,52.75219179908415"
    },
    {
      "school_osm_id": "215232318",
      "school_osm_type": "way",
      "school_name": "",
      "place_osm_id": "-59065",
      "place_admin_level": "2",
      "place_place": "",
      "place_name": "Беларусь",
      "lon": "26.41633137497884",
      "lat": "52.751856166456704",
      "bbox": "26.4153185,52.751513199084144,26.417356599999998,52.75219179908415"
    }
  ]
}