{
  "place": {
    "name": "Миловиды",
    "osm_id": "-7456732",
    "hierarchy": [
      "Миловидский сельский Совет",
      "Барановичский район",
      "Брестская область"
    ]
  },
  "geo": {
    "lat": "52.89153147186744",
    "lon": "25.85133092909792",
    "bbox": "25.851108999999997,52.8913799990853,25.8515488,52.891687399085285"
  },
  "group": [
    {
      "school_osm_id": "225998041",
      "school_osm_type": "way",
      "school_name": "УПК",
      "place_osm_id": "-8096123",
      "place_admin_level": "8",
      "place_place": "",
      "place_name": "Миловидский сельский Совет"
    },
    {
      "school_osm_id": "225998041",
      "school_osm_type": "way",
      "school_name": "УПК",
      "place_osm_id": "-7456732",
      "place_admin_level": "10",
      "place_place": "village",
      "place_name": "Миловиды"
    },
    {
      "school_osm_id": "225998041",
      "school_osm_type": "way",
      "school_name": "УПК",
      "place_osm_id": "-71116",
      "place_admin_level": "6",
      "place_place": "",
      "place_name": "Барановичский район"
    },
    {
      "school_osm_id": "225998041",
      "school_osm_type": "way",
      "school_name": "УПК",
      "place_osm_id": "-59189",
      "place_admin_level": "4",
      "place_place": "",
      "place_name": "Брестская область"
    },
    {
      "school_osm_id": "225998041",
      "school_osm_type": "way",
      "school_name": "УПК",
      "place_osm_id": "-59065",
      "place_admin_level": "2",
      "place_place": "",
      "place_name": "Беларусь"
    }
  ]
}