{
  "place": {
    "name": "Большая Зимница",
    "osm_id": "-7589498",
    "hierarchy": [
      "Свенский сельский Совет",
      "Славгородский район",
      "Могилёвская область"
    ]
  },
  "geo": {
    "lat": "53.327799358339234",
    "lon": "30.622393455202563",
    "bbox": "30.622090299999996,53.32769709910486,30.622696899999998,53.32790309910486"
  },
  "group": [
    {
      "school_osm_id": "241204031",
      "school_osm_type": "way",
      "school_name": "",
      "place_osm_id": "-8140432",
      "place_admin_level": "8",
      "place_place": "",
      "place_name": "Свенский сельский Совет"
    },
    {
      "school_osm_id": "241204031",
      "school_osm_type": "way",
      "school_name": "",
      "place_osm_id": "-7589498",
      "place_admin_level": "10",
      "place_place": "village",
      "place_name": "Большая Зимница"
    },
    {
      "school_osm_id": "241204031",
      "school_osm_type": "way",
      "school_name": "",
      "place_osm_id": "-70589",
      "place_admin_level": "6",
      "place_place": "",
      "place_name": "Славгородский район"
    },
    {
      "school_osm_id": "241204031",
      "school_osm_type": "way",
      "school_name": "",
      "place_osm_id": "-59162",
      "place_admin_level": "4",
      "place_place": "",
      "place_name": "Могилёвская область"
    },
    {
      "school_osm_id": "241204031",
      "school_osm_type": "way",
      "school_name": "",
      "place_osm_id": "-59065",
      "place_admin_level": "2",
      "place_place": "",
      "place_name": "Беларусь"
    }
  ]
}