{
  "place": {
    "name": "Вирков",
    "osm_id": "-7583367",
    "hierarchy": [
      "Несятский сельский Совет",
      "Кличевский район",
      "Могилёвская область"
    ]
  },
  "geo": {
    "lat": "53.462748204408534",
    "lon": "29.049040134577012",
    "bbox": "29.0488296,53.46261049911597,29.0492507,53.462885899116"
  },
  "group": [
    {
      "school_osm_id": "246769809",
      "school_osm_type": "way",
      "school_name": "",
      "place_osm_id": "-8144297",
      "place_admin_level": "8",
      "place_place": "",
      "place_name": "Несятский сельский Совет"
    },
    {
      "school_osm_id": "246769809",
      "school_osm_type": "way",
      "school_name": "",
      "place_osm_id": "-7583367",
      "place_admin_level": "10",
      "place_place": "village",
      "place_name": "Вирков"
    },
    {
      "school_osm_id": "246769809",
      "school_osm_type": "way",
      "school_name": "",
      "place_osm_id": "-70577",
      "place_admin_level": "6",
      "place_place": "",
      "place_name": "Кличевский район"
    },
    {
      "school_osm_id": "246769809",
      "school_osm_type": "way",
      "school_name": "",
      "place_osm_id": "-59162",
      "place_admin_level": "4",
      "place_place": "",
      "place_name": "Могилёвская область"
    },
    {
      "school_osm_id": "246769809",
      "school_osm_type": "way",
      "school_name": "",
      "place_osm_id": "-59065",
      "place_admin_level": "2",
      "place_place": "",
      "place_name": "Беларусь"
    }
  ]
}