{
  "place": {
    "name": "Ленино",
    "osm_id": "-7442978",
    "hierarchy": [
      "Ленинский сельский Совет",
      "Добрушский район",
      "Гомельская область"
    ]
  },
  "geo": {
    "lat": "52.181730024107424",
    "lon": "31.68206047749287"
  },
  "group": [
    {
      "school_osm_id": "284822746",
      "school_osm_type": "way",
      "school_name": "школьная мастерская",
      "place_osm_id": "-8065399",
      "place_admin_level": "8",
      "place_place": "",
      "place_name": "Ленинский сельский Совет",
      "lon": "31.68206047749287",
      "lat": "52.181730024107424",
      "bbox": "31.681879800000004,52.181627599103635,31.682239700000004,52.18183289910361"
    },
    {
      "school_osm_id": "284822746",
      "school_osm_type": "way",
      "school_name": "школьная мастерская",
      "place_osm_id": "-7442978",
      "place_admin_level": "10",
      "place_place": "village",
      "place_name": "Ленино",
      "lon": "31.68206047749287",
      "lat": "52.181730024107424",
      "bbox": "31.681879800000004,52.181627599103635,31.682239700000004,52.18183289910361"
    },
    {
      "school_osm_id": "284822746",
      "school_osm_type": "way",
      "school_name": "школьная мастерская",
      "place_osm_id": "-59161",
      "place_admin_level": "4",
      "place_place": "",
      "place_name": "Гомельская область",
      "lon": "31.68206047749287",
      "lat": "52.181730024107424",
      "bbox": "31.681879800000004,52.181627599103635,31.682239700000004,52.18183289910361"
    },
    {
      "school_osm_id": "284822746",
      "school_osm_type": "way",
      "school_name": "школьная мастерская",
      "place_osm_id": "-59092",
      "place_admin_level": "6",
      "place_place": "",
      "place_name": "Добрушский район",
      "lon": "31.68206047749287",
      "lat": "52.181730024107424",
      "bbox": "31.681879800000004,52.181627599103635,31.682239700000004,52.18183289910361"
    },
    {
      "school_osm_id": "284822746",
      "school_osm_type": "way",
      "school_name": "школьная мастерская",
      "place_osm_id": "-59065",
      "place_admin_level": "2",
      "place_place": "",
      "place_name": "Беларусь",
      "lon": "31.68206047749287",
      "lat": "52.181730024107424",
      "bbox": "31.681879800000004,52.181627599103635,31.682239700000004,52.18183289910361"
    }
  ]
}