{
  "place": {
    "name": "Минск",
    "osm_id": "-59195",
    "hierarchy": []
  },
  "geo": {
    "lat": "53.864106291108655",
    "lon": "27.56264762289665"
  },
  "group": [
    {
      "school_osm_id": "286070705",
      "school_osm_type": "way",
      "school_name": "",
      "place_osm_id": "-59202",
      "place_admin_level": "9",
      "place_place": "",
      "place_name": "Ленинский район",
      "lon": "27.56264762289665",
      "lat": "53.864106291108655"
    },
    {
      "school_osm_id": "286070705",
      "school_osm_type": "way",
      "school_name": "",
      "place_osm_id": "-59195",
      "place_admin_level": "4",
      "place_place": "city",
      "place_name": "Минск",
      "lon": "27.56264762289665",
      "lat": "53.864106291108655"
    },
    {
      "school_osm_id": "286070705",
      "school_osm_type": "way",
      "school_name": "",
      "place_osm_id": "-59065",
      "place_admin_level": "2",
      "place_place": "",
      "place_name": "Беларусь",
      "lon": "27.56264762289665",
      "lat": "53.864106291108655"
    }
  ]
}