{
  "place": {
    "name": "Ратичи",
    "osm_id": "-7511913",
    "hierarchy": [
      "Подлабенский сельский Совет",
      "Гродненский район",
      "Гродненская область"
    ]
  },
  "geo": {
    "lat": "53.76219679865582",
    "lon": "23.660181310545937"
  },
  "group": [
    {
      "school_osm_id": "286972930",
      "school_osm_type": "way",
      "school_name": "Ратичская средняя общеобразовательная школа",
      "place_osm_id": "-8025351",
      "place_admin_level": "8",
      "place_place": "",
      "place_name": "Подлабенский сельский Совет",
      "lon": "23.660181310545937",
      "lat": "53.76219679865582"
    },
    {
      "school_osm_id": "286972930",
      "school_osm_type": "way",
      "school_name": "Ратичская средняя общеобразовательная школа",
      "place_osm_id": "-7511913",
      "place_admin_level": "10",
      "place_place": "village",
      "place_name": "Ратичи",
      "lon": "23.660181310545937",
      "lat": "53.76219679865582"
    },
    {
      "school_osm_id": "286972930",
      "school_osm_type": "way",
      "school_name": "Ратичская средняя общеобразовательная школа",
      "place_osm_id": "-59275",
      "place_admin_level": "4",
      "place_place": "",
      "place_name": "Гродненская область",
      "lon": "23.660181310545937",
      "lat": "53.76219679865582"
    },
    {
      "school_osm_id": "286972930",
      "school_osm_type": "way",
      "school_name": "Ратичская средняя общеобразовательная школа",
      "place_osm_id": "-59273",
      "place_admin_level": "6",
      "place_place": "",
      "place_name": "Гродненский район",
      "lon": "23.660181310545937",
      "lat": "53.76219679865582"
    },
    {
      "school_osm_id": "286972930",
      "school_osm_type": "way",
      "school_name": "Ратичская средняя общеобразовательная школа",
      "place_osm_id": "-59065",
      "place_admin_level": "2",
      "place_place": "",
      "place_name": "Беларусь",
      "lon": "23.660181310545937",
      "lat": "53.76219679865582"
    }
  ]
}