{
  "place": {
    "name": "Жлобин",
    "osm_id": "-5598358",
    "hierarchy": [
      "Жлобинский район",
      "Гомельская область"
    ]
  },
  "geo": {
    "lat": "52.88346391101203",
    "lon": "30.03368347264062",
    "bbox": "30.032783300000002,52.88249589908514,30.0344963,52.88458929908518"
  },
  "group": [
    {
      "school_osm_id": "290876461",
      "school_osm_type": "way",
      "school_name": "Средняя школа № 2",
      "place_osm_id": "-5598358",
      "place_admin_level": "8",
      "place_place": "town",
      "place_name": "Жлобин"
    },
    {
      "school_osm_id": "290876461",
      "school_osm_type": "way",
      "school_name": "Средняя школа № 2",
      "place_osm_id": "-59167",
      "place_admin_level": "6",
      "place_place": "",
      "place_name": "Жлобинский район"
    },
    {
      "school_osm_id": "290876461",
      "school_osm_type": "way",
      "school_name": "Средняя школа № 2",
      "place_osm_id": "-59161",
      "place_admin_level": "4",
      "place_place": "",
      "place_name": "Гомельская область"
    },
    {
      "school_osm_id": "290876461",
      "school_osm_type": "way",
      "school_name": "Средняя школа № 2",
      "place_osm_id": "-59065",
      "place_admin_level": "2",
      "place_place": "",
      "place_name": "Беларусь"
    }
  ]
}