{
  "place": {
    "name": "Брест",
    "osm_id": "-72615",
    "hierarchy": [
      "Брестская область"
    ]
  },
  "geo": {
    "lat": "52.08722149911038",
    "lon": "23.687084199999997",
    "bbox": ""
  },
  "group": [
    {
      "school_osm_id": "306063250",
      "school_osm_type": "node",
      "school_name": "Школа №18",
      "place_osm_id": "-3626404",
      "place_admin_level": "9",
      "place_place": "",
      "place_name": "Ленинский район"
    },
    {
      "school_osm_id": "306063250",
      "school_osm_type": "node",
      "school_name": "Школа №18",
      "place_osm_id": "-72615",
      "place_admin_level": "6",
      "place_place": "city",
      "place_name": "Брест"
    },
    {
      "school_osm_id": "306063250",
      "school_osm_type": "node",
      "school_name": "Школа №18",
      "place_osm_id": "-59189",
      "place_admin_level": "4",
      "place_place": "",
      "place_name": "Брестская область"
    },
    {
      "school_osm_id": "306063250",
      "school_osm_type": "node",
      "school_name": "Школа №18",
      "place_osm_id": "-59065",
      "place_admin_level": "2",
      "place_place": "",
      "place_name": "Беларусь"
    }
  ]
}