{
  "place": {
    "name": "Большие Новосёлки",
    "osm_id": "-6823889",
    "hierarchy": [
      "Дзержинский сельский Совет",
      "Дзержинский район",
      "Минская область"
    ]
  },
  "geo": {
    "lat": "53.74014261047769",
    "lon": "27.114472659079166",
    "bbox": "27.112568099999997,53.739110999146526,27.1161837,53.74109709914676"
  },
  "group": [
    {
      "school_osm_id": "373893571",
      "school_osm_type": "way",
      "school_name": "",
      "place_osm_id": "-8139705",
      "place_admin_level": "8",
      "place_place": "",
      "place_name": "Дзержинский сельский Совет"
    },
    {
      "school_osm_id": "373893571",
      "school_osm_type": "way",
      "school_name": "",
      "place_osm_id": "-6823889",
      "place_admin_level": "10",
      "place_place": "village",
      "place_name": "Большие Новосёлки"
    },
    {
      "school_osm_id": "373893571",
      "school_osm_type": "way",
      "school_name": "",
      "place_osm_id": "-70563",
      "place_admin_level": "6",
      "place_place": "",
      "place_name": "Дзержинский район"
    },
    {
      "school_osm_id": "373893571",
      "school_osm_type": "way",
      "school_name": "",
      "place_osm_id": "-59752",
      "place_admin_level": "4",
      "place_place": "",
      "place_name": "Минская область"
    },
    {
      "school_osm_id": "373893571",
      "school_osm_type": "way",
      "school_name": "",
      "place_osm_id": "-59065",
      "place_admin_level": "2",
      "place_place": "",
      "place_name": "Беларусь"
    }
  ]
}