{
  "place": {
    "name": "Барановичи",
    "osm_id": "-3629362",
    "hierarchy": [
      "Брестская область"
    ]
  },
  "geo": {
    "lat": "53.11879620059448",
    "lon": "26.023353068400173",
    "bbox": "26.021828399999997,53.117852199092354,26.024781100000002,53.11974939909244"
  },
  "group": [
    {
      "school_osm_id": "380315312",
      "school_osm_type": "way",
      "school_name": "Школа № 16",
      "place_osm_id": "-3629362",
      "place_admin_level": "6",
      "place_place": "city",
      "place_name": "Барановичи"
    },
    {
      "school_osm_id": "380315312",
      "school_osm_type": "way",
      "school_name": "Школа № 16",
      "place_osm_id": "-59189",
      "place_admin_level": "4",
      "place_place": "",
      "place_name": "Брестская область"
    },
    {
      "school_osm_id": "380315312",
      "school_osm_type": "way",
      "school_name": "Школа № 16",
      "place_osm_id": "-59065",
      "place_admin_level": "2",
      "place_place": "",
      "place_name": "Беларусь"
    }
  ]
}