{
  "place": {
    "name": "Молодечно",
    "osm_id": "-6722552",
    "hierarchy": [
      "Молодечненский район",
      "Минская область"
    ]
  },
  "geo": {
    "lat": "54.305239581235284",
    "lon": "26.850563579336914",
    "bbox": "26.852714999999996,54.30677579924245,26.848384399999997,54.30400549924187"
  },
  "group": [
    {
      "school_osm_id": "388130343",
      "school_osm_type": "way",
      "school_name": "Школа №8",
      "place_osm_id": "-6722552",
      "place_admin_level": "8",
      "place_place": "city",
      "place_name": "Молодечно"
    },
    {
      "school_osm_id": "388130343",
      "school_osm_type": "way",
      "school_name": "Школа №8",
      "place_osm_id": "-70566",
      "place_admin_level": "6",
      "place_place": "",
      "place_name": "Молодечненский район"
    },
    {
      "school_osm_id": "388130343",
      "school_osm_type": "way",
      "school_name": "Школа №8",
      "place_osm_id": "-59752",
      "place_admin_level": "4",
      "place_place": "",
      "place_name": "Минская область"
    },
    {
      "school_osm_id": "388130343",
      "school_osm_type": "way",
      "school_name": "Школа №8",
      "place_osm_id": "-59065",
      "place_admin_level": "2",
      "place_place": "",
      "place_name": "Беларусь"
    }
  ]
}