{
  "place": "warning-school-without-place",
  "geo": {
    "lat": "53.611530233264645",
    "lon": "28.9700189709325",
    "bbox": "28.971639300000003,53.612625499131255,28.968608399999994,53.610626899131"
  },
  "group": [
    {
      "school_osm_id": "550706910",
      "school_osm_type": "way",
      "school_name": "",
      "place_osm_id": "-8144326",
      "place_admin_level": "8",
      "place_place": "",
      "place_name": "Капланецкий сельский Совет"
    },
    {
      "school_osm_id": "550706910",
      "school_osm_type": "way",
      "school_name": "",
      "place_osm_id": "-70575",
      "place_admin_level": "6",
      "place_place": "",
      "place_name": "Березинский район"
    },
    {
      "school_osm_id": "550706910",
      "school_osm_type": "way",
      "school_name": "",
      "place_osm_id": "-59752",
      "place_admin_level": "4",
      "place_place": "",
      "place_name": "Минская область"
    },
    {
      "school_osm_id": "550706910",
      "school_osm_type": "way",
      "school_name": "",
      "place_osm_id": "-59065",
      "place_admin_level": "2",
      "place_place": "",
      "place_name": "Беларусь"
    }
  ]
}