{
  "place": {
    "name": "Минск",
    "osm_id": "-59195",
    "hierarchy": []
  },
  "geo": {
    "lat": "53.904701599169826",
    "lon": "27.538364099999995",
    "bbox": ""
  },
  "group": [
    {
      "school_osm_id": "5879226285",
      "school_osm_type": "node",
      "school_name": "Музыкальная школа №12",
      "place_osm_id": "-59208",
      "place_admin_level": "9",
      "place_place": "",
      "place_name": "Московский район"
    },
    {
      "school_osm_id": "5879226285",
      "school_osm_type": "node",
      "school_name": "Музыкальная школа №12",
      "place_osm_id": "-59195",
      "place_admin_level": "4",
      "place_place": "city",
      "place_name": "Минск"
    },
    {
      "school_osm_id": "5879226285",
      "school_osm_type": "node",
      "school_name": "Музыкальная школа №12",
      "place_osm_id": "-59065",
      "place_admin_level": "2",
      "place_place": "",
      "place_name": "Беларусь"
    }
  ]
}