{
  "place": {
    "name": "Конюхи",
    "osm_id": "-7507282",
    "hierarchy": [
      "Конюховский сельский Совет",
      "Берестовицкий район",
      "Гродненская область"
    ]
  },
  "geo": {
    "lat": "53.393445284996275",
    "lon": "23.899507091592525"
  },
  "group": [
    {
      "school_osm_id": "686336993",
      "school_osm_type": "way",
      "school_name": "Конюховский учебно-педагогический комплекс ясли-сад - средняя школа",
      "place_osm_id": "-8025374",
      "place_admin_level": "8",
      "place_place": "",
      "place_name": "Конюховский сельский Совет",
      "lon": "23.899507091592525",
      "lat": "53.393445284996275"
    },
    {
      "school_osm_id": "686336993",
      "school_osm_type": "way",
      "school_name": "Конюховский учебно-педагогический комплекс ясли-сад - средняя школа",
      "place_osm_id": "-7507282",
      "place_admin_level": "10",
      "place_place": "village",
      "place_name": "Конюхи",
      "lon": "23.899507091592525",
      "lat": "53.393445284996275"
    },
    {
      "school_osm_id": "686336993",
      "school_osm_type": "way",
      "school_name": "Конюховский учебно-педагогический комплекс ясли-сад - средняя школа",
      "place_osm_id": "-70790",
      "place_admin_level": "6",
      "place_place": "",
      "place_name": "Берестовицкий район",
      "lon": "23.899507091592525",
      "lat": "53.393445284996275"
    },
    {
      "school_osm_id": "686336993",
      "school_osm_type": "way",
      "school_name": "Конюховский учебно-педагогический комплекс ясли-сад - средняя школа",
      "place_osm_id": "-59275",
      "place_admin_level": "4",
      "place_place": "",
      "place_name": "Гродненская область",
      "lon": "23.899507091592525",
      "lat": "53.393445284996275"
    },
    {
      "school_osm_id": "686336993",
      "school_osm_type": "way",
      "school_name": "Конюховский учебно-педагогический комплекс ясли-сад - средняя школа",
      "place_osm_id": "-59065",
      "place_admin_level": "2",
      "place_place": "",
      "place_name": "Беларусь",
      "lon": "23.899507091592525",
      "lat": "53.393445284996275"
    }
  ]
}