{
  "place": {
    "name": "Шамовщина",
    "osm_id": "-6688424",
    "hierarchy": [
      "Копачёвский сельский Совет",
      "Мстиславский район",
      "Могилёвская область"
    ]
  },
  "geo": {
    "lat": "54.046334074972854",
    "lon": "31.626381535624564"
  },
  "group": [
    {
      "school_osm_id": "766650122",
      "school_osm_type": "way",
      "school_name": "",
      "place_osm_id": "-8076010",
      "place_admin_level": "8",
      "place_place": "",
      "place_name": "Копачёвский сельский Совет",
      "lon": "31.626381535624564",
      "lat": "54.046334074972854",
      "bbox": "31.624891,54.04531629919266,31.627959399999998,54.047388799193016"
    },
    {
      "school_osm_id": "766650122",
      "school_osm_type": "way",
      "school_name": "",
      "place_osm_id": "-6688424",
      "place_admin_level": "10",
      "place_place": "village",
      "place_name": "Шамовщина",
      "lon": "31.626381535624564",
      "lat": "54.046334074972854",
      "bbox": "31.624891,54.04531629919266,31.627959399999998,54.047388799193016"
    },
    {
      "school_osm_id": "766650122",
      "school_osm_type": "way",
      "school_name": "",
      "place_osm_id": "-70616",
      "place_admin_level": "6",
      "place_place": "",
      "place_name": "Мстиславский район",
      "lon": "31.626381535624564",
      "lat": "54.046334074972854",
      "bbox": "31.624891,54.04531629919266,31.627959399999998,54.047388799193016"
    },
    {
      "school_osm_id": "766650122",
      "school_osm_type": "way",
      "school_name": "",
      "place_osm_id": "-59162",
      "place_admin_level": "4",
      "place_place": "",
      "place_name": "Могилёвская область",
      "lon": "31.626381535624564",
      "lat": "54.046334074972854",
      "bbox": "31.624891,54.04531629919266,31.627959399999998,54.047388799193016"
    },
    {
      "school_osm_id": "766650122",
      "school_osm_type": "way",
      "school_name": "",
      "place_osm_id": "-59065",
      "place_admin_level": "2",
      "place_place": "",
      "place_name": "Беларусь",
      "lon": "31.626381535624564",
      "lat": "54.046334074972854",
      "bbox": "31.624891,54.04531629919266,31.627959399999998,54.047388799193016"
    }
  ]
}