{
  "place": {
    "name": "Брест",
    "osm_id": "-72615",
    "hierarchy": [
      "Брестская область"
    ]
  },
  "geo": {
    "lat": "52.08569952023536",
    "lon": "23.72028908383544",
    "bbox": "23.720769599999997,52.08610189911048,23.7198471,52.08530799911053"
  },
  "group": [
    {
      "school_osm_id": "820221780",
      "school_osm_type": "way",
      "school_name": "Центр юных моряков с флотилией г. Бреста",
      "place_osm_id": "-3626405",
      "place_admin_level": "9",
      "place_place": "",
      "place_name": "Московский район"
    },
    {
      "school_osm_id": "820221780",
      "school_osm_type": "way",
      "school_name": "Центр юных моряков с флотилией г. Бреста",
      "place_osm_id": "-72615",
      "place_admin_level": "6",
      "place_place": "city",
      "place_name": "Брест"
    },
    {
      "school_osm_id": "820221780",
      "school_osm_type": "way",
      "school_name": "Центр юных моряков с флотилией г. Бреста",
      "place_osm_id": "-59189",
      "place_admin_level": "4",
      "place_place": "",
      "place_name": "Брестская область"
    },
    {
      "school_osm_id": "820221780",
      "school_osm_type": "way",
      "school_name": "Центр юных моряков с флотилией г. Бреста",
      "place_osm_id": "-59065",
      "place_admin_level": "2",
      "place_place": "",
      "place_name": "Беларусь"
    }
  ]
}